setup.py
django_maro.egg-info/PKG-INFO
django_maro.egg-info/SOURCES.txt
django_maro.egg-info/dependency_links.txt
django_maro.egg-info/namespace_packages.txt
django_maro.egg-info/top_level.txt
maro/__init__.py
maro/love/__init__.py
maro/love/django/__init__.py
maro/love/django/orm.py