Metadata-Version: 1.0
Name: django-maro
Version: 0.0.2
Summary: `django-maro` is utility for django.
Home-page: https://bitbucket.org/imagawa_yakata/django-maro
Author: oyakata(imagawa_yakata)
Author-email: imagawa.yakata+maro at gmail.com
License: PSL
Keywords: oyakata,maro,django
Platform: UNKNOWN
Classifier: Development Status :: 1 - Planning
Classifier: Natural Language :: Japanese
Classifier: Programming Language :: Python
